11l.py
_11l_to_cpp/parse.py
_11l_to_cpp/tokenizer.py
python_to_11l/parse.py
python_to_11l/tokenizer.py
11l-2021.3.dist-info/LICENSE.txt
11l-2021.3.dist-info/METADATA
11l-2021.3.dist-info/WHEEL
11l-2021.3.dist-info/top_level.txt
11l-2021.3.dist-info/RECORD
